tests/__init__.py
tests/test_blink_2fa_logging.py
tests/test_blink_integration.py
tests/test_css_sorting.py
tests/test_download_ssl_certificates.py
tests/test_duplicate_stdout_fix.py
tests/test_email_notification.py
tests/test_emulator_integration.py
tests/test_environment.py
tests/test_environment_version_detection.py
tests/test_flask_generic.py
tests/test_honeywell_integration.py
tests/test_honeywell_unit.py
tests/test_kumocloud_integration.py
tests/test_kumocloudv3_integration.py
tests/test_kumolocal_integration.py
tests/test_kumolocal_unit.py
tests/test_mmm_integration.py
tests/test_nest_env_integration.py
tests/test_nest_env_token_cache_unit.py
tests/test_nest_integration.py
tests/test_nest_oauth_refresh_unit.py
tests/test_nest_safety_temperature_unit.py
tests/test_nest_spam_mitigation_unit.py
tests/test_sht31_empty_ip.py
tests/test_sht31_enhanced_403_unit.py
tests/test_sht31_flask_server_integration.py
tests/test_sht31_flask_server_unit.py
tests/test_sht31_import_isolation.py
tests/test_sht31_integration.py
tests/test_sht31_missing_env_var.py
tests/test_sht31_path_selection.py
tests/test_ssl_certificate.py
tests/test_supervise.py
tests/test_supervisor_flask_server.py
tests/test_sys_modules_truncation.py
tests/test_thermostat_api.py
tests/test_thermostat_common.py
tests/test_utilities.py
tests/test_version_increment.py
tests/test_weather.py
tests/test_weather_integration.py
tests/test_wsgi_production.py
tests/test_yamllint_workflow.py
tests/unit_test_common.py
tests/unit_test_coverage.py
thermostatsupervisor/__init__.py
thermostatsupervisor/blink.py
thermostatsupervisor/blink_config.py
thermostatsupervisor/email_notification.py
thermostatsupervisor/emulator.py
thermostatsupervisor/emulator_config.py
thermostatsupervisor/environment.py
thermostatsupervisor/flask_generic.py
thermostatsupervisor/honeywell.py
thermostatsupervisor/honeywell_config.py
thermostatsupervisor/kumocloud.py
thermostatsupervisor/kumocloud_config.py
thermostatsupervisor/kumocloudv3.py
thermostatsupervisor-1.0.13.dist-info/licenses/LICENSE
thermostatsupervisor-1.0.13.dist-info/METADATA
thermostatsupervisor-1.0.13.dist-info/WHEEL
thermostatsupervisor-1.0.13.dist-info/top_level.txt
thermostatsupervisor-1.0.13.dist-info/RECORD
