Metadata-Version: 2.4
Name: Thermostatsupervisor
Version: 1.0.13
Summary: Monitor remote thermostats and correct deviations from schedule.
Home-page: https://github.com/cjkrolak/ThermostatSupervisor
Author: Christopher Krolak
Author-email: cjkrolak@gmail.com
Classifier: License :: OSI Approved :: MIT License
Classifier: Operating System :: OS Independent
Classifier: Development Status :: 5 - Production/Stable
Classifier: Intended Audience :: Developers
Classifier: Intended Audience :: End Users/Desktop
Classifier: Environment :: Console
Classifier: Framework :: Flask
Classifier: Framework :: IDLE
Classifier: Natural Language :: English
Classifier: Programming Language :: Python :: 3.12
Classifier: Programming Language :: Python :: 3.13
Classifier: Topic :: Home Automation
Requires-Python: >=3.9
License-File: LICENSE
Requires-Dist: dnspython
Requires-Dist: munch
Requires-Dist: psutil
Dynamic: license-file
